{
  "resourceType": "ClinicalUseDefinition",
  "id": "db01113-peripheral-vascular-disease",
  "type": "indication",
  "subject": [
    {
      "reference": "MedicationKnowledge/db01113"
    }
  ],
  "indication": {
    "diseaseSymptomProcedure": {
      "concept": {
        "text": "peripheral vascular disease"
      }
    }
  },
  "extension": [
    {
      "url": "https://nztxgnn.yao.care/fhir/StructureDefinition/evidence-level",
      "valueCode": "L5"
    },
    {
      "url": "https://nztxgnn.yao.care/fhir/StructureDefinition/txgnn-score",
      "valueDecimal": 0.5
    }
  ]
}